pheval/__init__.py
pheval/cli.py
pheval/cli_pheval.py
pheval/cli_pheval_utils.py
pheval/config_parser.py
pheval/run_metadata.py
pheval/analyse/__init__.py
pheval/analyse/benchmark.py
pheval/analyse/benchmark_db_manager.py
pheval/analyse/benchmark_output_type.py
pheval/analyse/binary_classification_curves.py
pheval/analyse/binary_classification_stats.py
pheval/analyse/generate_plots.py
pheval/analyse/generate_rank_comparisons.py
pheval/analyse/rank_stats.py
pheval/analyse/run_data_parser.py
pheval/implementations/__init__.py
pheval/implementations/pheval_class_resolver.py
pheval/infra/__init__.py
pheval/infra/exomiserdb.py
pheval/post_processing/__init__.py
pheval/post_processing/mondo_mapping.py
pheval/post_processing/phenopacket_truth_set.py
pheval/post_processing/post_processing.py
pheval/post_processing/validate_result_format.py
pheval/prepare/__init__.py
pheval/prepare/create_noisy_phenopackets.py
pheval/prepare/create_spiked_vcf.py
pheval/prepare/custom_exceptions.py
pheval/prepare/prepare_corpus.py
pheval/prepare/update_phenopacket.py
pheval/resources/hgnc_complete_set.txt
pheval/resources/metadata.json
pheval/resources/mondo.sssom.tsv
pheval/resources/alternate_ouputs/CADA_results.txt
pheval/resources/alternate_ouputs/DeepPVP_results.txt
pheval/resources/alternate_ouputs/OVA_results.txt
pheval/resources/alternate_ouputs/Phen2Gene_results.json
pheval/resources/alternate_ouputs/Phenolyzer_results.txt
pheval/resources/alternate_ouputs/lirical_results.tsv
pheval/resources/alternate_ouputs/svanna_results.tsv
pheval/runners/__init__.py
pheval/runners/runner.py
pheval/utils/__init__.py
pheval/utils/docs_gen.py
pheval/utils/docs_gen.sh
pheval/utils/exomiser.py
pheval/utils/file_utils.py
pheval/utils/logger.py
pheval/utils/phenopacket_utils.py
pheval/utils/semsim_utils.py
pheval/utils/utils.py
pheval-0.7.2.dist-info/METADATA
pheval-0.7.2.dist-info/WHEEL
pheval-0.7.2.dist-info/entry_points.txt
pheval-0.7.2.dist-info/licenses/LICENSE
pheval-0.7.2.dist-info/RECORD
