Metadata-Version: 2.4
Name: pheval
Version: 0.7.2
Author-email: Yasemin Bridges <y.bridges@qmul.ac.uk>, Julius Jacobsen <j.jacobsen@qmul.ac.uk>, Nico Matentzoglu <nicolas.matentzoglu@gmail.com>, Vinícius de Souza <souzadevinicius@gmail.com>
License-File: LICENSE
Requires-Python: <4.0.0,>=3.10
Requires-Dist: class-resolver>=0.4.2
Requires-Dist: click>=8.1.3
Requires-Dist: deprecation>=2.1.0
Requires-Dist: duckdb<2,>=1.0.0
Requires-Dist: google<4,>=3.0.0
Requires-Dist: jaydebeapi>=1.2.3
Requires-Dist: matplotlib<4,>=3.7.0
Requires-Dist: oaklib>=0.5.6
Requires-Dist: pandas>=1.5.1
Requires-Dist: phenopackets<3,>=2.0.2
Requires-Dist: plotly<6,>=5.13.0
Requires-Dist: polars~=1.23
Requires-Dist: pyaml<22,>=21.10.1
Requires-Dist: pyarrow<20,>=19.0.1
Requires-Dist: pyserde<0.10,>=0.9.8
Requires-Dist: scikit-learn<2,>=1.4.0
Requires-Dist: seaborn<0.13,>=0.12.2
Requires-Dist: tqdm>=4.64.1
